{"nodes":[{"id":"components_commitfooter","label":"CommitFooter.tsx","file_type":"code","source_file":"src/components/CommitFooter.tsx","source_location":"L1"},{"id":"components_commitfooter_commitfooterprops","label":"CommitFooterProps","file_type":"code","source_file":"src/components/CommitFooter.tsx","source_location":"L5"},{"id":"components_commitfooter_commitfooter","label":"CommitFooter()","file_type":"code","source_file":"src/components/CommitFooter.tsx","source_location":"L12"}],"edges":[{"source":"components_commitfooter","target":"lucide_react","relation":"imports_from","confidence":"EXTRACTED","source_file":"src/components/CommitFooter.tsx","source_location":"L1","weight":1},{"source":"components_commitfooter","target":"c_tech_grow_tools_dib_src_types_db_ts","relation":"imports_from","confidence":"EXTRACTED","source_file":"src/components/CommitFooter.tsx","source_location":"L2","weight":1},{"source":"components_commitfooter","target":"types_db_pendingchange","relation":"imports","confidence":"EXTRACTED","source_file":"src/components/CommitFooter.tsx","source_location":"L2","weight":1},{"source":"components_commitfooter","target":"c_tech_grow_tools_dib_src_components_commitfooter_css","relation":"imports_from","confidence":"EXTRACTED","source_file":"src/components/CommitFooter.tsx","source_location":"L3","weight":1},{"source":"components_commitfooter","target":"components_commitfooter_commitfooterprops","relation":"contains","confidence":"EXTRACTED","source_file":"src/components/CommitFooter.tsx","source_location":"L5","weight":1},{"source":"components_commitfooter","target":"components_commitfooter_commitfooter","relation":"contains","confidence":"EXTRACTED","source_file":"src/components/CommitFooter.tsx","source_location":"L12","weight":1}]}