{"nodes":[{"id":"hooks_usedatagridstate","label":"useDataGridState.ts","file_type":"code","source_file":"src/hooks/useDataGridState.ts","source_location":"L1"},{"id":"hooks_usedatagridstate_operatorsfortype","label":"operatorsForType()","file_type":"code","source_file":"src/hooks/useDataGridState.ts","source_location":"L10"},{"id":"hooks_usedatagridstate_cellstr","label":"cellStr()","file_type":"code","source_file":"src/hooks/useDataGridState.ts","source_location":"L20"},{"id":"hooks_usedatagridstate_makekey","label":"makeKey()","file_type":"code","source_file":"src/hooks/useDataGridState.ts","source_location":"L26"},{"id":"hooks_usedatagridstate_cellid","label":"cellId()","file_type":"code","source_file":"src/hooks/useDataGridState.ts","source_location":"L30"},{"id":"hooks_usedatagridstate_buildrangeset","label":"buildRangeSet()","file_type":"code","source_file":"src/hooks/useDataGridState.ts","source_location":"L34"},{"id":"hooks_usedatagridstate_snapshot","label":"Snapshot","file_type":"code","source_file":"src/hooks/useDataGridState.ts","source_location":"L42"},{"id":"hooks_usedatagridstate_editstate","label":"EditState","file_type":"code","source_file":"src/hooks/useDataGridState.ts","source_location":"L48"},{"id":"hooks_usedatagridstate_makeeditstate","label":"makeEditState()","file_type":"code","source_file":"src/hooks/useDataGridState.ts","source_location":"L53"},{"id":"hooks_usedatagridstate_usedatagridstateoptions","label":"UseDataGridStateOptions","file_type":"code","source_file":"src/hooks/useDataGridState.ts","source_location":"L57"},{"id":"hooks_usedatagridstate_usedatagridstate","label":"useDataGridState()","file_type":"code","source_file":"src/hooks/useDataGridState.ts","source_location":"L77"}],"edges":[{"source":"hooks_usedatagridstate","target":"react","relation":"imports_from","confidence":"EXTRACTED","source_file":"src/hooks/useDataGridState.ts","source_location":"L1","weight":1},{"source":"hooks_usedatagridstate","target":"c_tech_grow_tools_dib_src_types_db_ts","relation":"imports_from","confidence":"EXTRACTED","source_file":"src/hooks/useDataGridState.ts","source_location":"L2","weight":1},{"source":"hooks_usedatagridstate","target":"types_db_pendingchange","relation":"imports","confidence":"EXTRACTED","source_file":"src/hooks/useDataGridState.ts","source_location":"L2","weight":1},{"source":"hooks_usedatagridstate","target":"types_db_columninfo","relation":"imports","confidence":"EXTRACTED","source_file":"src/hooks/useDataGridState.ts","source_location":"L2","weight":1},{"source":"hooks_usedatagridstate","target":"types_db_gridfilter","relation":"imports","confidence":"EXTRACTED","source_file":"src/hooks/useDataGridState.ts","source_location":"L2","weight":1},{"source":"hooks_usedatagridstate","target":"types_db_filteroperator","relation":"imports","confidence":"EXTRACTED","source_file":"src/hooks/useDataGridState.ts","source_location":"L2","weight":1},{"source":"hooks_usedatagridstate","target":"types_db_tablerelation","relation":"imports","confidence":"EXTRACTED","source_file":"src/hooks/useDataGridState.ts","source_location":"L2","weight":1},{"source":"hooks_usedatagridstate","target":"hooks_usedatagridstate_operatorsfortype","relation":"contains","confidence":"EXTRACTED","source_file":"src/hooks/useDataGridState.ts","source_location":"L10","weight":1},{"source":"hooks_usedatagridstate","target":"hooks_usedatagridstate_cellstr","relation":"contains","confidence":"EXTRACTED","source_file":"src/hooks/useDataGridState.ts","source_location":"L20","weight":1},{"source":"hooks_usedatagridstate","target":"hooks_usedatagridstate_makekey","relation":"contains","confidence":"EXTRACTED","source_file":"src/hooks/useDataGridState.ts","source_location":"L26","weight":1},{"source":"hooks_usedatagridstate","target":"hooks_usedatagridstate_cellid","relation":"contains","confidence":"EXTRACTED","source_file":"src/hooks/useDataGridState.ts","source_location":"L30","weight":1},{"source":"hooks_usedatagridstate","target":"hooks_usedatagridstate_buildrangeset","relation":"contains","confidence":"EXTRACTED","source_file":"src/hooks/useDataGridState.ts","source_location":"L34","weight":1},{"source":"hooks_usedatagridstate","target":"hooks_usedatagridstate_snapshot","relation":"contains","confidence":"EXTRACTED","source_file":"src/hooks/useDataGridState.ts","source_location":"L42","weight":1},{"source":"hooks_usedatagridstate","target":"hooks_usedatagridstate_editstate","relation":"contains","confidence":"EXTRACTED","source_file":"src/hooks/useDataGridState.ts","source_location":"L48","weight":1},{"source":"hooks_usedatagridstate","target":"hooks_usedatagridstate_makeeditstate","relation":"contains","confidence":"EXTRACTED","source_file":"src/hooks/useDataGridState.ts","source_location":"L53","weight":1},{"source":"hooks_usedatagridstate","target":"hooks_usedatagridstate_usedatagridstateoptions","relation":"contains","confidence":"EXTRACTED","source_file":"src/hooks/useDataGridState.ts","source_location":"L57","weight":1},{"source":"hooks_usedatagridstate","target":"hooks_usedatagridstate_usedatagridstate","relation":"contains","confidence":"EXTRACTED","source_file":"src/hooks/useDataGridState.ts","source_location":"L77","weight":1},{"source":"hooks_usedatagridstate_buildrangeset","target":"hooks_usedatagridstate_cellid","relation":"calls","confidence":"EXTRACTED","source_file":"src/hooks/useDataGridState.ts","source_location":"L38","weight":1}]}